revTongYi/__init__.py
revTongYi/entity.py
revTongYi/errors.py
revTongYi/qianwen.py
revTongYi/wanxiang.py
revtongyi-0.1.2.0.dist-info/METADATA
revtongyi-0.1.2.0.dist-info/WHEEL
revtongyi-0.1.2.0.dist-info/licenses/LICENSE
revtongyi-0.1.2.0.dist-info/RECORD
