Metadata-Version: 2.3
Name: revTongYi
Version: 0.1.2.0
Summary: 阿里通义千问逆向工程API
Project-URL: Homepage, https://github.com/leeeduke/revTongYi
Project-URL: Bug Tracker, https://github.com/leeeduke/revTongYi/issues
Author-email: xw5xr6 <xw5xr6@hotmail.com>, leeeduke <dukelee652@gmail.com>
License-File: LICENSE
Classifier: License :: OSI Approved :: GNU Affero General Public License v3
Classifier: Operating System :: OS Independent
Classifier: Programming Language :: Python :: 3
Requires-Python: >=3.7
Requires-Dist: fake-useragent
Requires-Dist: filetype
Requires-Dist: requests
